music_muse_rest_api_client/__init__.py
music_muse_rest_api_client/api/__init__.py
music_muse_rest_api_client/api/жанры/__init__.py
music_muse_rest_api_client/api/жанры/apps_music_api_routes_genres_add_new_genre.py
music_muse_rest_api_client/api/жанры/apps_music_api_routes_genres_get_filtered_genre.py
music_muse_rest_api_client/api/жанры/apps_music_api_routes_genres_get_genre_pages.py
music_muse_rest_api_client/api/жанры/apps_music_api_routes_genres_update_genre.py
music_muse_rest_api_client/api/исполнители/__init__.py
music_muse_rest_api_client/api/исполнители/apps_music_api_routes_artists_add_new_artist.py
music_muse_rest_api_client/api/исполнители/apps_music_api_routes_artists_get_artist_pages.py
music_muse_rest_api_client/api/исполнители/apps_music_api_routes_artists_get_filtered_artist.py
music_muse_rest_api_client/api/исполнители/apps_music_api_routes_artists_update_artist.py
music_muse_rest_api_client/api/контент/__init__.py
music_muse_rest_api_client/api/контент/apps_music_api_routes_content_add_new_audio.py
music_muse_rest_api_client/api/контент/apps_music_api_routes_content_add_new_image.py
music_muse_rest_api_client/api/контент/apps_music_api_routes_content_add_new_video.py
music_muse_rest_api_client/api/контент/apps_music_api_routes_content_get_audio_pages.py
music_muse_rest_api_client/api/контент/apps_music_api_routes_content_get_filtered_audio.py
music_muse_rest_api_client/api/контент/apps_music_api_routes_content_get_filtered_image.py
music_muse_rest_api_client/api/контент/apps_music_api_routes_content_get_filtered_video.py
music_muse_rest_api_client/api/контент/apps_music_api_routes_content_get_images_pages.py
music_muse_rest_api_client/api/контент/apps_music_api_routes_content_get_video_pages.py
music_muse_rest_api_client/api/лейблы/__init__.py
music_muse_rest_api_client/api/лейблы/apps_music_api_routes_labels_add_new_label.py
music_muse_rest_api_client/api/лейблы/apps_music_api_routes_labels_get_filtered_labels.py
music_muse_rest_api_client-2025.2.2.post2.dist-info/METADATA
music_muse_rest_api_client-2025.2.2.post2.dist-info/WHEEL
music_muse_rest_api_client-2025.2.2.post2.dist-info/RECORD
